{
  "coords": {
    "system": "LV95",
    "x_min": 255.5,
    "x_max": 964.5,
    "x_count": 710,
    "y_min": -159.5,
    "y_max": 479.5,
    "y_count": 640
  },
  "areas": [
    {
      "color": "9e849a",
      "shapes": [
        [
          {
            "i": 269,
            "j": 438,
            "d": "NLNNLN",
            "o": "9900",
            "l": 0
          }
        ],
        [
          {
            "i": 279,
            "j": 360,
            "d": "NLOMNLNLNLNLOMNNNNNNMOLNKMLNMOLNLNLNLLLLLLMKLL",
            "o": "991134528353599113365340",
            "l": 0
          }
        ],
        [
          {
            "i": 281,
            "j": 426,
            "d": "NLOMNLNLNLNLNNMOMONNNLNLOMNLNLOMOMOMOMNLNLNNNNNLNLOMNNNNNNNNNNNNNNNNNNLNLNLNLNLNLNLNLNLNLLLLLLLLLLLLLLLLKMLNLNLLLLLLLLLLLLLNMOMOLNKMLNLNLNMOLNLLLLLLLLLLNLNLLLLLMK",
            "o": "4503546354115999616446439863728253901126731009272480933090933150018336009450999092",
            "l": 0
          }
        ],
        [
          {
            "i": 301,
            "j": 402,
            "d": "NLNNLN",
            "o": "6583",
            "l": 0
          }
        ],
        [
          {
            "i": 303,
            "j": 400,
            "d": "NLOMNNLNKM",
            "o": "995440",
            "l": 0
          }
        ],
        [
          {
            "i": 303,
            "j": 434,
            "d": "NLNNLN",
            "o": "5511",
            "l": 0
          }
        ],
        [
          {
            "i": 307,
            "j": 398,
            "d": "NLNNLN",
            "o": "8941",
            "l": 0
          }
        ],
        [
          {
            "i": 319,
            "j": 394,
            "d": "NLNLNLOMNNLNLNMOLNLNLNLLMK",
            "o": "98563166000068",
            "l": 0
          }
        ],
        [
          {
            "i": 321,
            "j": 456,
            "d": "NLOMNNLNLNLNLL",
            "o": "99900009",
            "l": 0
          }
        ],
        [
          {
            "i": 325,
            "j": 390,
            "d": "NLNNLN",
            "o": "3701",
            "l": 0
          }
        ],
        [
          {
            "i": 333,
            "j": 472,
            "d": "NLNLNLNLNLNLNLNNMOLNLNNNOMNLNLNLMKNLNLNLNNNNNNNNNNMOLNLNLNLNLNLNLNLNNNNNNNOMNNMONNOMOMNNNNNNNNNNNNNNLNLNLNKMLNMOMOLNLLLLLLLLLLLLLLMKLLLLLLLLMKMKLLLNLNLLLLKMLLLLLLMKNLNLNLNLLLKMLNLNLL",
            "o": "77418999023821478759906480005513244903537165471649000077422573360935655327414741839951187744",
            "l": 0
          }
        ],
        [
          {
            "i": 333,
            "j": 490,
            "d": "NLNLMKNLNNMOMOLNKM",
            "o": "9964631010",
            "l": 0
          }
        ],
        [
          {
            "i": 353,
            "j": 478,
            "d": "NLNLNLNLNLOMOMNNLNLNLNLNLNKMKM",
            "o": "6321697941211132",
            "l": 0
          }
        ],
        [
          {
            "i": 363,
            "j": 472,
            "d": "NLOMNNLNKM",
            "o": "996114",
            "l": 0
          }
        ],
        [
          {
            "i": 363,
            "j": 484,
            "d": "NLNLNLNLNLNLNLOMOMOMNNMOLNLNLNLNLNKMKMKMKM",
            "o": "9947458857900068726300",
            "l": 0
          }
        ],
        [
          {
            "i": 429,
            "j": 464,
            "d": "NLOMNNNNNNMOLNLNLNKMLLMKMK",
            "o": "99726357300921",
            "l": 0
          }
        ],
        [
          {
            "i": 437,
            "j": 486,
            "d": "NLOMNNNNNNMOLNKMLLLLLL",
            "o": "991690776009",
            "l": 0
          }
        ],
        [
          {
            "i": 441,
            "j": 466,
            "d": "NLOMNNMOLNLLLL",
            "o": "72812165",
            "l": 0
          }
        ],
        [
          {
            "i": 441,
            "j": 692,
            "d": "NLNNLN",
            "o": "5744",
            "l": 0
          }
        ],
        [
          {
            "i": 447,
            "j": 694,
            "d": "NLNLNLNNNNNNLNLNLNLLLL",
            "o": "149904345328",
            "l": 0
          }
        ],
        [
          {
            "i": 449,
            "j": 544,
            "d": "NLNLMKNLOMNNMOLNLNLNLNLNLL",
            "o": "77230163546326",
            "l": 0
          }
        ],
        [
          {
            "i": 453,
            "j": 496,
            "d": "NLNLNLOMNNMONNNNLNKMKMKMLL",
            "o": "33672668322763",
            "l": 0
          }
        ],
        [
          {
            "i": 459,
            "j": 574,
            "d": "NLNNLN",
            "o": "3731",
            "l": 0
          }
        ],
        [
          {
            "i": 459,
            "j": 618,
            "d": "NLOMOMNLNLNLNLNNMONNNNNNNNMOLNKMLNMOLNLNNNOMOMNNLNLNMONNNNLNLNLNKMLLLLLLLLLLLLLLMKMKMKNLNLMKNLNLLLKMKM",
            "o": "9949625619076300760081590088134103454180967833661060",
            "l": 0
          }
        ],
        [
          {
            "i": 461,
            "j": 592,
            "d": "NLNNLN",
            "o": "9900",
            "l": 0
          }
        ],
        [
          {
            "i": 465,
            "j": 660,
            "d": "NLOMOMNNNNOMOMOMOMOMNNMOLNLNMOMOMONNOMNLMKMKNLNNMONNNNLNLNMOLNKMKMKMKMKMKMKMLLMKLLKMLLMKNLNLMKMKLLKMLL",
            "o": "6619147541278998112143990851494176347936474553444654",
            "l": 0
          }
        ],
        [
          {
            "i": 471,
            "j": 686,
            "d": "NLNLNLOMOMOMOMOMNLNLOMNLNLNLNLOMNNLNLNMOLNLNLNKMLNLNKMKMKMKMLNLNLNLNKMLLMK",
            "o": "30121285345111249006522199577378866092",
            "l": 0
          }
        ],
        [
          {
            "i": 475,
            "j": 638,
            "d": "NLOMNNLNKM",
            "o": "659002",
            "l": 0
          }
        ],
        [
          {
            "i": 475,
            "j": 644,
            "d": "NLOMOMNNMOLNLLLLKM",
            "o": "6626131483",
            "l": 0
          }
        ],
        [
          {
            "i": 491,
            "j": 732,
            "d": "NLNLNLNNNNOMNNMOLNKMLLLLKM",
            "o": "96990337264270",
            "l": 0
          }
        ],
        [
          {
            "i": 497,
            "j": 738,
            "d": "NLNNLN",
            "o": "8453",
            "l": 0
          }
        ],
        [
          {
            "i": 499,
            "j": 660,
            "d": "NLOMOMNNNNNLNLNNMOLNLNLNKMLLLLKMLL",
            "o": "351661380257571980",
            "l": 0
          }
        ],
        [
          {
            "i": 499,
            "j": 706,
            "d": "NLNLNLOMNLNLNLNLNNMOLNLNLNKMLNLNKM",
            "o": "769924324800006442",
            "l": 0
          }
        ],
        [
          {
            "i": 499,
            "j": 740,
            "d": "NLOMOMOMNNLNLNLNKMKMLL",
            "o": "327983100309",
            "l": 0
          }
        ],
        [
          {
            "i": 505,
            "j": 750,
            "d": "NLNLNLNLNLNNNNNNMOLNLNLNLLLLKM",
            "o": "7676990815886197",
            "l": 0
          }
        ],
        [
          {
            "i": 511,
            "j": 704,
            "d": "NLOMNNLNKM",
            "o": "849001",
            "l": 0
          }
        ],
        [
          {
            "i": 511,
            "j": 744,
            "d": "NLNNLN",
            "o": "9900",
            "l": 0
          }
        ],
        [
          {
            "i": 513,
            "j": 754,
            "d": "NLOMNNMOLNKMLL",
            "o": "99473108",
            "l": 0
          }
        ],
        [
          {
            "i": 517,
            "j": 734,
            "d": "NLNNLN",
            "o": "9900",
            "l": 0
          }
        ],
        [
          {
            "i": 517,
            "j": 738,
            "d": "NLNNLN",
            "o": "7311",
            "l": 0
          }
        ],
        [
          {
            "i": 521,
            "j": 762,
            "d": "NLNNLN",
            "o": "5811",
            "l": 0
          }
        ],
        [
          {
            "i": 531,
            "j": 768,
            "d": "NLNNMOLNLL",
            "o": "573532",
            "l": 0
          }
        ],
        [
          {
            "i": 537,
            "j": 802,
            "d": "NLNNNNNNLNKMLL",
            "o": "32790055",
            "l": 0
          }
        ],
        [
          {
            "i": 547,
            "j": 422,
            "d": "NLOMNNNNOMNNNNNNMOMOLNKMKMLLMKLLKMLLNLNLLL",
            "o": "1674338905342531609908",
            "l": 0
          }
        ],
        [
          {
            "i": 559,
            "j": 514,
            "d": "NLNLNLNLNLNNNNNNNNNNLNKMKMLNLNLLLL",
            "o": "620199055700577417",
            "l": 0
          }
        ],
        [
          {
            "i": 579,
            "j": 444,
            "d": "NLNNMOLNLL",
            "o": "881355",
            "l": 0
          }
        ],
        [
          {
            "i": 633,
            "j": 652,
            "d": "NLNLMKNLNNNNOMOMNNLNKMLNMOLNLNNNNNMOLNLLLLLLMKMKLL",
            "o": "99699099900000049013809890",
            "l": 0
          }
        ],
        [
          {
            "i": 637,
            "j": 602,
            "d": "NLOMNNMOLNLLLL",
            "o": "99900090",
            "l": 0
          }
        ],
        [
          {
            "i": 641,
            "j": 568,
            "d": "NLNLNLNLLLLLNLOMNNMOMONNOMNNMONNNNNNOMOMNNNNNNLNLNLNLNLNLLLLKMKMLLLLKMKMLLMKLLLLMK",
            "o": "449926769050290256145481499983666687182383",
            "l": 0
          }
        ],
        [
          {
            "i": 643,
            "j": 630,
            "d": "NLNLNLNNMOMOMONNOMNNMONNNNNNOMNNLNKMLNMOLNKMKMKMLLMKLLLLMKMKMKMKMK",
            "o": "9999033568259099000400045304978667",
            "l": 0
          }
        ],
        [
          {
            "i": 659,
            "j": 662,
            "d": "NLNNLN",
            "o": "9900",
            "l": 0
          }
        ],
        [
          {
            "i": 661,
            "j": 660,
            "d": "NLNNLN",
            "o": "7722",
            "l": 0
          }
        ],
        [
          {
            "i": 661,
            "j": 734,
            "d": "NLOMOMNNNNOMOMNLNLNNNNOMNLNLOMNNMONNOMNNMONNNNNNNNNNNNLNLNNNOMNNMONNNNMOLNLNNNNNLNLNLNKMKMLNLNLNLNKMLLLLLNLNKMKMLNLNKMLLMKNLNLLLLNLNLLLLLLNLNLNLNNNNOMOMOMNLMKLLLLLLLLLLLLMKLLKMKMLLMKNLNLLLLLMKMKLLLLLLKM",
            "o": "999545696842678815990053619007233661246900000553000630063303644930090996818852994709279640999338973600",
            "l": 0
          }
        ],
        [
          {
            "i": 663,
            "j": 580,
            "d": "NLNNLN",
            "o": "4477",
            "l": 0
          }
        ],
        [
          {
            "i": 665,
            "j": 588,
            "d": "NLNLNLNLMKMKNLOMNNMOMOMOMOMOMOLNKMKMLLLLLL",
            "o": "4212403304550784174428",
            "l": 0
          }
        ],
        [
          {
            "i": 665,
            "j": 766,
            "d": "NLNNLN",
            "o": "9900",
            "l": 0
          }
        ],
        [
          {
            "i": 667,
            "j": 180,
            "d": "NLOMNLNLNNMOLNKMKM",
            "o": "6611466653",
            "l": 0
          }
        ],
        [
          {
            "i": 669,
            "j": 660,
            "d": "NLNLMKNLNNMONNOMNLNLNNMOMONNNNNNNNLNLNMOMOLNLNMOMONNNNNNNNLNKMLLLLLLMKMKMKLLLLMKLLLLNLNLLLLLLLLLLL",
            "o": "99488461256156359003011423905340909443374099272470",
            "l": 0
          }
        ],
        [
          {
            "i": 673,
            "j": 176,
            "d": "NLNLNLNNMOLNKM",
            "o": "11119848",
            "l": 0
          }
        ],
        [
          {
            "i": 675,
            "j": 590,
            "d": "NLNLMKMKMKNLOMOMOMNLMKNLNNMOMOLNLNMOMONNNLNLNLNLNLMKMKLLLLNLNLNLOMNNMONNNNMOMONNOMNNNNOMNLMKNLOMNNMONNOMNNLNLNLNLNLNLNMONNNLNLNNNNNLMKMKMKNLNLMKMKNLOMOMNLNLNLNLOMNLNLOMOMOMNLNLNLNLOMNNNNOMOMNNNNOMNNNNOMOMNNNNNLNLOMNLNLOMOMNNLNLNLNLNMOMONNNLNLNLNLOMOMNLMKNLNLNLOMNNMOLNLNNNNNLNLNMOMOMOMOLNLLLLLLNLNLLLKMLNMOLNLNLNLNLNLLMKLLKMLNLNLLMKLLLNLNLNMONNNNMOLNLNMOLNKMLNLNKMKMLLMKNLNLLLKMLNMOLNKMKMLLMKNLOMNLMKMKNLNLNLNLMKMKNLNLNLNLLLLNLNLNLNLNLNLNMOLNLNLNKMLNLNLNLNLNLNKMLNLNLLMKLLKMLLMKNLNLMKLLLNLNKMKMLNMOLNLNMOLNLNLNLLMKLLLNLNLLLLLNMONNNNMOLNLLLLKMLNLNLNMOMOMOMOMOMOLNKMLNLNLLMKMKLLLLMKMKLLLLMKMKMKMKLLLLMKNLNLLLLLLLKMKMKMKMKMLL",
            "o": "121835496478544363029445397236699907187816811399287173388846626670349993299311116147222633890646715567902795994814998744556673263999000790044172230997340005542742872619755044553119834099619881270999146522354359913535799900327013232577127157638500005007470091984299922326463572002141300922398435147409861671269823",
            "l": 0
          }
        ],
        [
          {
            "i": 683,
            "j": 662,
            "d": "NLOMNNNNOMNNLNKMLNNNOMOMNNNNNNMONNNNMONNNNNNNNLNKMKMKMLLLLKMKMLLMKMKNLNLLLLLLLLLMKMKLL",
            "o": "68759900041023838357279000018542675117436542",
            "l": 0
          }
        ],
        [
          {
            "i": 701,
            "j": 620,
            "d": "NLOMNNNNNNMOMOMOMOLNKMLLMKMKMKMKLL",
            "o": "147190247355402247",
            "l": 0
          }
        ],
        [
          {
            "i": 709,
            "j": 582,
            "d": "NLNNLN",
            "o": "6914",
            "l": 0
          }
        ],
        [
          {
            "i": 709,
            "j": 678,
            "d": "NLOMNNNNOMNNMOMOLNKMKMLLLLLLMK",
            "o": "7447081565828187",
            "l": 0
          }
        ],
        [
          {
            "i": 711,
            "j": 616,
            "d": "NLNNLN",
            "o": "9900",
            "l": 0
          }
        ],
        [
          {
            "i": 713,
            "j": 312,
            "d": "NLNLNLNNMOLNKM",
            "o": "99881440",
            "l": 0
          }
        ],
        [
          {
            "i": 717,
            "j": 296,
            "d": "NLNNLN",
            "o": "4059",
            "l": 0
          }
        ],
        [
          {
            "i": 719,
            "j": 306,
            "d": "NLNNLN",
            "o": "6635",
            "l": 0
          }
        ],
        [
          {
            "i": 721,
            "j": 288,
            "d": "NLOMNNLNKM",
            "o": "554566",
            "l": 0
          }
        ],
        [
          {
            "i": 723,
            "j": 804,
            "d": "NLOMNLNLNNNNOMNNMOLNKMKMLNLNLLLLLL",
            "o": "658883252117555466",
            "l": 0
          }
        ],
        [
          {
            "i": 725,
            "j": 294,
            "d": "NLNLNLNLNLOMNNMOLNKMLNLNLNLNLL",
            "o": "5511110977877772",
            "l": 0
          }
        ],
        [
          {
            "i": 731,
            "j": 658,
            "d": "NLNLNLNLNLNNMONNNNLNLNLNKMKMLL",
            "o": "2477676390000736",
            "l": 0
          }
        ],
        [
          {
            "i": 731,
            "j": 844,
            "d": "NLOMNNNNOMNNNNNNMONNOMNLMKMKNLOMNNMONNNNNNOMNNNNNNNNOMNNNNNNMOMONNNNNNNNLNKMKMLLLLLNLNLNLNLNLNKMLNLNKMKMLLLLLLLLLLMKMKMKMKMKLLLLLLLLLLKMLNLNLLMKMKMKNLNLLL",
            "o": "635364653713399990074118263904555726014156420000500871664114678091575009942226",
            "l": 0
          }
        ],
        [
          {
            "i": 733,
            "j": 680,
            "d": "NLOMNLMKLLLLNLNLLLLLNLOMNLNLOMOMNNNNNNNNNNNNNNNNOMNNNNNNNNNNMONNOMOMNNNNNNNNOMNNMONNNNNNNNNNOMNNNNOMNLNLNNMOLNLNLNLLLLLNLNLNLNKMLNLNKMLLLLKMLLLLLLLLLLLLKMLNMOLNLLLLLLMKMKLLLLLLKMLNLNLLLLKMLLLLLLMKLLLLLLKMLL",
            "o": "75594376156721236353565726155637199054090463738865399066623462116754383637095700097542638700974581335709",
            "l": 0
          }
        ],
        [
          {
            "i": 735,
            "j": 610,
            "d": "NLNNLN",
            "o": "9900",
            "l": 0
          }
        ],
        [
          {
            "i": 737,
            "j": 800,
            "d": "NLOMOMOMNNMONNOMNNMOLNLNMOMOMONNNNNNNLNLNLNLOMNNNNNNMONNNNMONNNNNNNNNNNNNNNNLNLNNNNNNNNNMONNNNMONNNNNNOMOMNNMOMOLNLNLNKMLLLLKMKMLLMKLLKMLLLLLNLNLLLLKMLLLLLLLLLLLLLLNLNLMKNLNLLLKMKMLLLLLLLLLLLLLLLLLLMKLLLLNLOMNLNLNLLLLLMKMKLLLLLLLLMKLL",
            "o": "7222906390436406334997607718628247455900036524905462722600000935372662841570933835515443621572480936109932223686337417",
            "l": 0
          }
        ],
        [
          {
            "i": 755,
            "j": 808,
            "d": "NLOMOMNNNNNNNNNNMONNOMNLNLNNNNNNNNNNLNLNLNKMKMLLLLKMLLMKLLKMLLMKLLKMLL",
            "o": "363815735812990548120078563509440945",
            "l": 0
          }
        ],
        [
          {
            "i": 759,
            "j": 596,
            "d": "NLNNLN",
            "o": "5613",
            "l": 0
          }
        ],
        [
          {
            "i": 761,
            "j": 604,
            "d": "NLNNLN",
            "o": "9900",
            "l": 0
          }
        ],
        [
          {
            "i": 763,
            "j": 330,
            "d": "NLNNLN",
            "o": "6053",
            "l": 0
          }
        ],
        [
          {
            "i": 765,
            "j": 328,
            "d": "NLNNLN",
            "o": "0635",
            "l": 0
          }
        ],
        [
          {
            "i": 765,
            "j": 606,
            "d": "NLOMOMNNNNOMNNMOLNLNLNKMKMLLMKLLLL",
            "o": "440380563678526544",
            "l": 0
          }
        ],
        [
          {
            "i": 771,
            "j": 598,
            "d": "NLOMOMNNLNLNNNOMNNLNKMKMLLLLLL",
            "o": "5739009255536171",
            "l": 0
          }
        ],
        [
          {
            "i": 783,
            "j": 658,
            "d": "NLNLNLOMOMNLNLNNMOMOMOLNKMLNLNLLLLKMLL",
            "o": "78246499058757742771",
            "l": 0
          }
        ],
        [
          {
            "i": 783,
            "j": 704,
            "d": "NLNLMKNLNNNNOMNNMOLNLNMONNNLNLOMOMNNMONNNNNNNNMONNNNMONNOMNNLNKMKMLLLLKMLLLLKMLLLLLLMKLLLNLNKMLLMKLLLLMKMK",
            "o": "996990281149815746371645932399000059097527619840984614",
            "l": 0
          }
        ],
        [
          {
            "i": 789,
            "j": 348,
            "d": "NLNNLN",
            "o": "8711",
            "l": 0
          }
        ],
        [
          {
            "i": 795,
            "j": 628,
            "d": "NLNNMOLNLL",
            "o": "990009",
            "l": 0
          }
        ],
        [
          {
            "i": 797,
            "j": 662,
            "d": "NLOMOMOMOMOMOMNLNLNNNNNNMOLNKMKMKMKMLLLLKMLNLNKMLL",
            "o": "36331597783535585216877414",
            "l": 0
          }
        ],
        [
          {
            "i": 799,
            "j": 622,
            "d": "NLNLNLNLNLOMOMOMOMNNNNNNLNLNLNKMKMLNMOMONNOMNNLNLNLNLNNNNNMOLNLNNNNNLNLNLNKMKMKMLLMKNLNLNLOMNLLLLLNLNLLLKMKMLLNLNLMKMKLLLL",
            "o": "42447898390900313457285365600535827510686687991458893418722327",
            "l": 0
          }
        ],
        [
          {
            "i": 799,
            "j": 696,
            "d": "NLOMNNMOLNKMLL",
            "o": "64666645",
            "l": 0
          }
        ],
        [
          {
            "i": 803,
            "j": 700,
            "d": "NLOMNLNLNNNNOMNNNNOMNNMOLNLNMOLNLNMOMOLNLLMKLLLLMKLLLLMKLLKMLL",
            "o": "55299018355115514000099275521815",
            "l": 0
          }
        ],
        [
          {
            "i": 811,
            "j": 722,
            "d": "NLNLMKNLOMOMNLLLLLMKNLNNNNOMNNLNLNNNNNLNLNLNLNMOLNKMLLLLKM",
            "o": "662422150999026241524563001701",
            "l": 0
          }
        ],
        [
          {
            "i": 813,
            "j": 672,
            "d": "NLOMOMNNLNLNLNKMLL",
            "o": "4119005451",
            "l": 0
          }
        ],
        [
          {
            "i": 815,
            "j": 682,
            "d": "NLNLNLOMNNNNOMOMNLNLOMOMNNLNLNLNKMLNLNKMKMKMKMLLLL",
            "o": "73999086113490064873183093",
            "l": 0
          }
        ],
        [
          {
            "i": 815,
            "j": 698,
            "d": "NLNLMKMKNLNLLLLLNLOMNNMOMOMONNOMOMNLNLNLLLKMLLNLNLNLNNNNNNMOMOMOMOMOMOMONNNNLNKMLLMKLLLLLLKMLLMKLLLNLNKMKM",
            "o": "764999409990300791219718999073006814790024272926974134",
            "l": 0
          }
        ],
        [
          {
            "i": 817,
            "j": 608,
            "d": "NLOMNNMOLNLLLL",
            "o": "88620094",
            "l": 0
          }
        ],
        [
          {
            "i": 819,
            "j": 602,
            "d": "NLNNLN",
            "o": "4376",
            "l": 0
          }
        ],
        [
          {
            "i": 821,
            "j": 606,
            "d": "NLNNLN",
            "o": "9900",
            "l": 0
          }
        ],
        [
          {
            "i": 821,
            "j": 724,
            "d": "NLOMNNLNKM",
            "o": "476145",
            "l": 0
          }
        ],
        [
          {
            "i": 835,
            "j": 634,
            "d": "NLNLNLNLMKMKNLNLNLOMNNNNNNMONNOMNLMKLLKMLLLLLLLLLLNLNLMKNLOMNLNLOMOMOMNLLLLLMKMKMKMKNLNLNLOMNLMKNLNNMONNNNNNNNMOMONNNNMOMOLNLNMOMOMOMOMOMOLNLNLNLNNNOMNLNLOMNNMONNNNMOLNLNMONNNNMOLNLNMOLNLNMOLNLNMOLNLNLNKMLNMOLNLLMKMKLLLNLNKMKMKMLLMKMKNLNLNLNLMKNLNLNLNLMKNLNLMKLLLNMOLNLNLNLNLNLNMOLNKMLNMOMOLNKMKMLLLLLLNLNLMKMKMKLLKMLLNLNLNLNLMKNLOMNLNLNLLLKMKMLNLNLNMOMOLNLLMKLL",
            "o": "76412965989062180015267184596311127335611267881399051816759065776255312778954146170344905138126578765580227915104546867411234105442881111225009955464109933209096013791113076643735826",
            "l": 0
          }
        ],
        [
          {
            "i": 839,
            "j": 700,
            "d": "NLNLMKNLOMOMNNLNLNNNNNNNOMOMNNNNOMOMNLNLNLLLKMLLNLNLMKNLOMNNNNNLNLNNMOLNLNMONNNNMONNNNLNKMLNLNLNMOMOLNLNLNKMLLLLKMKMLLNLOMOMOMNLMKMKMKLLLNLNKMKMLLLLKMLNLNKMKMLLMKMKLL",
            "o": "149654811376159247242270994463619900015904900654165400056318877236598734096500309968",
            "l": 0
          }
        ],
        [
          {
            "i": 843,
            "j": 680,
            "d": "NLNNLN",
            "o": "9900",
            "l": 0
          }
        ],
        [
          {
            "i": 847,
            "j": 680,
            "d": "NLOMNLNLNNNNOMNNMOLNKMLNLNKMKMLLMK",
            "o": "361382581116425495",
            "l": 0
          }
        ],
        [
          {
            "i": 847,
            "j": 734,
            "d": "NLOMOMOMOMNNNNNNMOMOMOLNLNLNKMLLLLLLLLKMLLMKNLNLLL",
            "o": "88615629003550037264533134",
            "l": 0
          }
        ],
        [
          {
            "i": 855,
            "j": 172,
            "d": "NLNNLN",
            "o": "3377",
            "l": 0
          }
        ],
        [
          {
            "i": 855,
            "j": 694,
            "d": "NLNNLN",
            "o": "3755",
            "l": 0
          }
        ],
        [
          {
            "i": 857,
            "j": 750,
            "d": "NLOMOMNLLLLLNLOMNLNLOMOMNNNNNNNNNNNNOMOMNNMOMOMOLNKMLLLLKMKMLLLLLLMKLLLLLLLNMOMOLNKMKMLLLL",
            "o": "2211345794645562635690555306611726272764321093",
            "l": 0
          }
        ],
        [
          {
            "i": 861,
            "j": 172,
            "d": "NLNNLN",
            "o": "2367",
            "l": 0
          }
        ],
        [
          {
            "i": 861,
            "j": 672,
            "d": "NLNNNNNNMOLNKMLLMK",
            "o": "9906343557",
            "l": 0
          }
        ],
        [
          {
            "i": 865,
            "j": 670,
            "d": "NLNLMKNLNLNLNLMKLLLLNLNLNLNNNNNLNLNLNLNLMKMKNLNNMONNNLNLOMNNNNNNMOMOLNLNMONNNNMOLNLLLLKMKMKMLNMOMOMOLNLNLNKMLLMKLLKMLNMOLNKMLL",
            "o": "8846411130996481012456990348957900247490226477999947000966800036",
            "l": 0
          }
        ],
        [
          {
            "i": 865,
            "j": 684,
            "d": "NLOMOMNLNLOMOMNNLNLNMOMOMOLNKMLLMKLLKMLNMOLNLLMKMK",
            "o": "78327848015664683068823753",
            "l": 0
          }
        ],
        [
          {
            "i": 867,
            "j": 738,
            "d": "NLNNLN",
            "o": "9900",
            "l": 0
          }
        ],
        [
          {
            "i": 869,
            "j": 606,
            "d": "NLNNLN",
            "o": "9900",
            "l": 0
          }
        ],
        [
          {
            "i": 871,
            "j": 704,
            "d": "NLNNLN",
            "o": "9900",
            "l": 0
          }
        ],
        [
          {
            "i": 873,
            "j": 706,
            "d": "NLNLMKNLNLMKNLOMNLLLLLMKNLNLNLNLNLOMNLNLOMOMOMNLNLOMNLNLOMNNMONNOMOMNLMKNLNLLLLLMKMKMKMKNLOMNLNLOMOMNLNLNLNLOMOMNNNNNNMOMOMONNNNNNNLNLNLMKNLNNNNOMNLMKNLOMNNNNNNMOMOLNLNMOLNLNLNKMLNMONNNNLNLNLNLNMOLNLNMOLNLNMOMOLNKMLLLLLLLLLLNLNLMKNLNLMKNLNLMKLLLNLNKMKMLNLNLLMKLLKMLNNNNNNNNNMOMOLNLNLNLNMOLNLLLLLLLLKMLLNLOMNLLLLLNLNLLLKMKMKMLNNNNNLNKMKMLNNNOMOMNNMONNNNLNLNLNKMLNLNKMLNMONNNLNLNNNNOMNNNNNLMKNLOMNNNNOMOMNNNNNNMOMOLNLNMONNNNNNNNNNNNLNKMLLLLLLLLLNLNLNMOMONNNNMOLNLNMOMOMOMOLNLNLNLLLLLLLLLLLLLLLLKMKMKMLLLLKMLLLLLLLLLLLLLLLLLNLNLLMKNLNLLLLLMKLLKMKMKMLLMKNLNLNLNLLLLNLNLLLLLLMKMK",
            "o": "869786883237889978222023842154574668992459869988896264114463787901110990311561681135855449769003070074789699161389562199427005855753683357447667735438633118566157681867773371384100231878015524626889012754275992753743336265465059003874300009745522951185095281097009731842785089956480090936",
            "l": 0
          }
        ],
        [
          {
            "i": 873,
            "j": 774,
            "d": "NLNNNNNNLNKMLL",
            "o": "78542136",
            "l": 0
          }
        ],
        [
          {
            "i": 875,
            "j": 304,
            "d": "NLOMNNLNKM",
            "o": "154633",
            "l": 0
          }
        ],
        [
          {
            "i": 875,
            "j": 868,
            "d": "NLOMOMNNNNOMNLNLNLNLOMNNMOLNLNNNNNLNLNLNLNMOLNKMLLLLLLLLLLLLLLMKLL",
            "o": "9987421119981367900435000917270930",
            "l": 0
          }
        ],
        [
          {
            "i": 879,
            "j": 172,
            "d": "NLNNLN",
            "o": "3366",
            "l": 0
          }
        ],
        [
          {
            "i": 881,
            "j": 300,
            "d": "NLNNLN",
            "o": "5645",
            "l": 0
          }
        ],
        [
          {
            "i": 881,
            "j": 304,
            "d": "NLNNLN",
            "o": "6810",
            "l": 0
          }
        ],
        [
          {
            "i": 893,
            "j": 662,
            "d": "NLNLNLNNNNOMNLMKNLNLMKMKNLOMOMNNMOLNLNMOLNLNMOMOLNLNLNLNLNKMLLMKLLKMLL",
            "o": "558915007746772326673787367400193637",
            "l": 0
          }
        ],
        [
          {
            "i": 905,
            "j": 196,
            "d": "NLOMOMOMOMNNLNKMKMKMKM",
            "o": "447799000225",
            "l": 0
          }
        ],
        [
          {
            "i": 905,
            "j": 756,
            "d": "NLOMNNMOLNLLLL",
            "o": "55546545",
            "l": 0
          }
        ],
        [
          {
            "i": 909,
            "j": 648,
            "d": "NLNNLN",
            "o": "7763",
            "l": 0
          }
        ],
        [
          {
            "i": 909,
            "j": 776,
            "d": "NLNLNLNLMKNLOMNLNLNLNLOMNNMONNOMOMNLNLNNNNNNLNLNMONNNNLNLNLNLNMOLNKMKMLNNNNNLNLNMOLNKMKMLLLLLLLLLLLLLLMKMKMKLL",
            "o": "43110995319990628999090060900668786707127333170932489336",
            "l": 0
          }
        ],
        [
          {
            "i": 915,
            "j": 644,
            "d": "NLNNLN",
            "o": "7810",
            "l": 0
          }
        ],
        [
          {
            "i": 917,
            "j": 728,
            "d": "NLNNLN",
            "o": "9900",
            "l": 0
          }
        ],
        [
          {
            "i": 919,
            "j": 744,
            "d": "NLNLNLNNNNNNMOMOMOLNLNLNLLLLLLMKMK",
            "o": "334836264011466525",
            "l": 0
          }
        ],
        [
          {
            "i": 921,
            "j": 652,
            "d": "NLNNLN",
            "o": "7862",
            "l": 0
          }
        ],
        [
          {
            "i": 923,
            "j": 648,
            "d": "NLOMNNLNLNLNLL",
            "o": "44236885",
            "l": 0
          }
        ],
        [
          {
            "i": 925,
            "j": 654,
            "d": "NLNLMKNLNNMOMOMOLNKMLL",
            "o": "992681661554",
            "l": 0
          }
        ],
        [
          {
            "i": 931,
            "j": 730,
            "d": "NLOMOMOMNLLLLLNLNLNLNLNLOMNLNLNLNLNNMONNOMOMNLNLOMOMNNNNNLNLOMNLNLNNNNNNMOMOLNLNLNLLLLLNMOLNKMLNMONNNNMOLNLLLLLLLLLNMOMONNNNNNOMNNMONNNNMONNNNLNLNMOLNLLLLLNLNKMLLMKLLLLLLLLLLLLLLLLNLNLMKMKMKLLLLLLKMLLLLLNLNKMLNLNLLLLLNLNLLLLLL",
            "o": "689953199775400389033125879013686571513553614442626300909755743463834754250096316346474351586421628239624009653472",
            "l": 0
          }
        ],
        [
          {
            "i": 931,
            "j": 788,
            "d": "NLNNNNNLNLOMNNNNNLNLNNMOMOLNKMKMKMLLLLKMLL",
            "o": "2862327715815235309861",
            "l": 0
          }
        ],
        [
          {
            "i": 937,
            "j": 744,
            "d": "NLNNNNNLNLNNNNNNNNNNNNNNNNNNNNOMNNNNNNLNLNLNKMKMLLLLKMLLLLKMLLLLKMLLMKMKMK",
            "o": "89629901814553566690031217708109534121",
            "l": 0
          }
        ],
        [
          {
            "i": 939,
            "j": 310,
            "d": "NLNNLN",
            "o": "4453",
            "l": 0
          }
        ],
        [
          {
            "i": 939,
            "j": 692,
            "d": "NLNLMKNLOMOMNLMKMKMKNLOMNLNLNLNLNNMOMOLNLNMOMOMOMOMONNNNLNLNLNLNLNLNLNLNLNKMKMKMLLNLNLMKLLLLMK",
            "o": "567356642377001463546776316701363376202909947182",
            "l": 0
          }
        ],
        [
          {
            "i": 941,
            "j": 296,
            "d": "NLOMNNLNKM",
            "o": "754332",
            "l": 0
          }
        ],
        [
          {
            "i": 941,
            "j": 710,
            "d": "NLNNNNNNLNLNMOLNLLMKMK",
            "o": "894237442882",
            "l": 0
          }
        ],
        [
          {
            "i": 945,
            "j": 742,
            "d": "NLNLNLNNMOLNLNLNLL",
            "o": "6258168445",
            "l": 0
          }
        ],
        [
          {
            "i": 947,
            "j": 278,
            "d": "NLNLNLNNMOLNKM",
            "o": "77881332",
            "l": 0
          }
        ],
        [
          {
            "i": 955,
            "j": 232,
            "d": "NLOMOMNNMOLNKMLLLL",
            "o": "2444555185",
            "l": 0
          }
        ],
        [
          {
            "i": 959,
            "j": 666,
            "d": "NLNNLN",
            "o": "6334",
            "l": 0
          }
        ],
        [
          {
            "i": 961,
            "j": 774,
            "d": "NLNLNLOMOMOMNLNLOMOMNLMKNLNLNLNLMKNLOMOMOMNLMKNLNNNNNNNNOMNLNLNLNLOMNNNNOMNNNNNNMOLNLNLNLNLNLNLNLNLNLNLNLNLNKMLNLNKMKMKMLLLLKMKMKMLNLNLNMOMOLNKMKMLLLLLLLLLLLLKMLL",
            "o": "7336246995119976664314999090127845471482400332364565532621300978584467871259271875",
            "l": 0
          }
        ],
        [
          {
            "i": 969,
            "j": 750,
            "d": "NLOMNNMOMOLNLLLLLL",
            "o": "0033700925",
            "l": 0
          }
        ],
        [
          {
            "i": 971,
            "j": 742,
            "d": "NLNLNLNLNLNLNLNLMKMKMKMKMKMKNLNLMKNLOMOMNNNNNNMOMONNOMOMOMNNNNOMNNNNOMNLNLNNNNOMOMNNMOMOMOMOLNLNNNNNMOLNLLLLKMLNLNKMKMKMLNLNKMLNMOLNLNLNKMKMKMLNLNLLLLKMLLLLKMLLMKMKLLLLLL",
            "o": "44332224289622732886271745443921815268337905547783311618422387488000285500980940942473",
            "l": 0
          }
        ],
        [
          {
            "i": 971,
            "j": 746,
            "d": "NLNNLN",
            "o": "5744",
            "l": 0
          }
        ],
        [
          {
            "i": 975,
            "j": 784,
            "d": "NLNNLN",
            "o": "9900",
            "l": 0
          }
        ],
        [
          {
            "i": 999,
            "j": 794,
            "d": "NLOMNNNNOMOMNNLNKMLNLNKMKMLLMK",
            "o": "9990279003333091",
            "l": 0
          }
        ],
        [
          {
            "i": 1013,
            "j": 774,
            "d": "NLNNMOLNLL",
            "o": "990009",
            "l": 0
          }
        ],
        [
          {
            "i": 1015,
            "j": 760,
            "d": "NLNLNLOMOMNNNNOMNNMOMOLNKMLNLNLLLLKMLLMKLL",
            "o": "8778446490300700957423",
            "l": 0
          }
        ],
        [
          {
            "i": 1017,
            "j": 802,
            "d": "NLNLMKNLOMNLNLOMNLNLNLNLOMOMNLLLLLNLNLNLNNNNOMOMNNNNNLLLLLLLLLLLLLMKMKLLLLMKMKLLLLMKMKMKMKMKNLOMNLNLOMNLNLNLNLNLMKLLKMLLMKLLLNLNLLLLKMKMLNLNKMKMLLLLLLNLOMNLMKMKMKNLNLMKMKMKLLLLNLNLLLKMKMKMLLMKNLNLNLNNNNNNNNOMNNNNOMNNMOMOMONNNLNLOMNLLLLLNLNLMKNLNLMKNLOMOMNNNNNNMOMONNNNNNNNNNNNNNNLNLOMOMOMNLNLOMOMOMOMOMNNNNNLNLNNNNNNNNOMOMNNNNNLNLNNNNNNNNOMNNNNOMNLNLOMNNMOMOMOMONNNNMONNNNMONNNNNNNNNNNNNNNNNNNNNNNNMOMONNNNNNNNMOMOLNKMKMLLLLKMKMLLLLKMLLNLNLLLKMKMLLNLNLLLLLLLLLLLLLMKLLKMLLLLLLLLLLLLLNLNKMLNMOLNKMKMKMKMKMLNLNLNLNKMLLMKLLKMLLLLLLLLKMKMKMKMKMLNMOLNLNMOLNLNMONNNLMKNLNNMOMONNNNMOMOMOMOMOMONNNNMOMONNNNMONNOMNNNNNNNNOMNNMOMONNNLNLOMOMOMOMOMNLNLNLLLLLMKMKLLLLNLNLLLKMLLNLNLLLLLLLLLMKMKNLOMNLNLNNNNNNNNNNMOMONNNNNNNNLNLNNNOMNNMOMONNNNMONNNNMOMOLNKMKMLNMOLNLNMOMONNNNLNKMLNLNKMLNNNOMOMNNMONNNNMONNNNMOMOLNKMKMLLLLKMKMLLMKMKLLKMLLNLNLLLKMLNLNLLMKMKMKLLLLLLLLMKLLKMLLMKMKLLLLNLOMNLLLKMLNLNKMKMKMKMLLMKLLLLMKLLLLMKLLKMLNMOLNLNMOMOMOMOMOMOMOLNLNLNLNMOLNKMLNLNLLMKLLKMLLLLKMKMKMLLLLLLLLLLLLLLLL",
            "o": "743752571579983348668414643246561875195609984634237462129661818009727633090995254621483099602747999905399026571567710666231034555332373814649954199873482179236247705906439011247133149091763828172734714290908855094609809918309917266551871931873284221302200000956090961278571686647259901724450038327842848345272309996342155309960996638529009999399046900081900638217366466130781113890068880124227157164446095184170995465286523834453645099598600250099264092677777642330001132360092853302275273356",
            "l": 0
          }
        ],
        [
          {
            "i": 1029,
            "j": 678,
            "d": "NLNNLN",
            "o": "7732",
            "l": 0
          }
        ],
        [
          {
            "i": 1045,
            "j": 696,
            "d": "NLNNLN",
            "o": "9900",
            "l": 0
          }
        ],
        [
          {
            "i": 1063,
            "j": 660,
            "d": "NLNLNLNLMKNLNNNNOMNNMOLNLNNNOMNNNNOMOMNNNNNNNNNNMOMOLNLNMOMOMONNNLNLOMNNMOMONNOMNLNLNLLLLLMKNLNLNLNLNLNNMONNNNLNLNMOLNLNNNNNLNLNLNLNNNNNNNOMOMOMOMNLNLOMNNLNLNMOLNLNLNLNMOLNLNLNLNMONNNLNLNNMONNOMOMOMNNMOMOLNKMKMLNLNLLLLLLLLKMKMKMKMKMKMLLMKMKMKMKNLOMNLLLKMKMLNLNLNLNLLMKLLLLMKMKMKMKNLNLLLLLLLLLLLKMLNLNLNLNLNLNLNLNLLMKMKNLNLLLLLNLNLMKNLNLMKNLNLMKLLKMKMLLNLNLNLNLMKMKLLKMLNLNKMLLMK",
            "o": "8641477379076026615908127624036811037837000148862243495028008614877258995877636500016488853166390024380058315655120150994343981765400923773166453838873120025668615665342632097286222213144635",
            "l": 0
          }
        ],
        [
          {
            "i": 1079,
            "j": 654,
            "d": "NLNLNLOMNNLNLNNNNNMOLNLLLLKMLL",
            "o": "9843446790009836",
            "l": 0
          }
        ],
        [
          {
            "i": 1093,
            "j": 774,
            "d": "NLNNLN",
            "o": "9900",
            "l": 0
          }
        ],
        [
          {
            "i": 1097,
            "j": 782,
            "d": "NLOMOMOMNLMKNLNLNLOMNNMONNNNMOMOLNKMLNLNLNLNLNLNKMLLLLLLMKMKLL",
            "o": "99559555994689077770066000909620",
            "l": 0
          }
        ],
        [
          {
            "i": 1099,
            "j": 776,
            "d": "NLOMNNMOLNKMLL",
            "o": "34640046",
            "l": 0
          }
        ],
        [
          {
            "i": 1103,
            "j": 764,
            "d": "NLNNLN",
            "o": "6463",
            "l": 0
          }
        ],
        [
          {
            "i": 1109,
            "j": 766,
            "d": "NLNNLN",
            "o": "9900",
            "l": 0
          }
        ],
        [
          {
            "i": 1115,
            "j": 706,
            "d": "NLOMNNMOLNLNLNLLMK",
            "o": "9954000098",
            "l": 0
          }
        ],
        [
          {
            "i": 1117,
            "j": 736,
            "d": "NLNLNLNLMKMKNLOMNLNLNNNNOMNNLNLNLNLNLNKMLNMOLNLNLNKMLL",
            "o": "7522489964436923522157987309",
            "l": 0
          }
        ],
        [
          {
            "i": 1121,
            "j": 794,
            "d": "NLNNLN",
            "o": "9900",
            "l": 0
          }
        ],
        [
          {
            "i": 1123,
            "j": 718,
            "d": "NLNNLN",
            "o": "8831",
            "l": 0
          }
        ],
        [
          {
            "i": 1131,
            "j": 780,
            "d": "NLNNMONNNNLNKMLLMK",
            "o": "3251811368",
            "l": 0
          }
        ],
        [
          {
            "i": 1133,
            "j": 774,
            "d": "NLNLNLNNMOLNLNLNLL",
            "o": "5879026009",
            "l": 0
          }
        ],
        [
          {
            "i": 1137,
            "j": 780,
            "d": "NLNLMKNLNNMOMOLNKM",
            "o": "9985653120",
            "l": 0
          }
        ],
        [
          {
            "i": 1139,
            "j": 788,
            "d": "NLNNLN",
            "o": "8721",
            "l": 0
          }
        ],
        [
          {
            "i": 1149,
            "j": 736,
            "d": "NLNNLN",
            "o": "9900",
            "l": 0
          }
        ],
        [
          {
            "i": 1157,
            "j": 730,
            "d": "NLNLMKNLOMNNLNLNNNNNLNKMKM",
            "o": "99356906915350",
            "l": 0
          }
        ],
        [
          {
            "i": 1157,
            "j": 744,
            "d": "NLNNLN",
            "o": "9900",
            "l": 0
          }
        ],
        [
          {
            "i": 1159,
            "j": 740,
            "d": "NLOMNNLNLNLNLL",
            "o": "37734009",
            "l": 0
          }
        ],
        [
          {
            "i": 1163,
            "j": 394,
            "d": "NLNNLN",
            "o": "8822",
            "l": 0
          }
        ],
        [
          {
            "i": 1165,
            "j": 396,
            "d": "NLNNLN",
            "o": "9900",
            "l": 0
          }
        ]
      ]
    },
    {
      "color": "2a00fa",
      "shapes": [
        [
          {
            "i": 673,
            "j": 176,
            "d": "NLNNLN",
            "o": "5554",
            "l": 1
          }
        ],
        [
          {
            "i": 675,
            "j": 174,
            "d": "NLNNLN",
            "o": "5555",
            "l": 1
          }
        ],
        [
          {
            "i": 691,
            "j": 590,
            "d": "NLOMNNNNNNNNOMNLNLNNNNNNLNKMLNLNLLLLKMKMLLMKLL",
            "o": "756419134762376341996507",
            "l": 1
          }
        ],
        [
          {
            "i": 727,
            "j": 292,
            "d": "NLNLNLOMNNLNLNLNKM",
            "o": "6677369836",
            "l": 1
          }
        ],
        [
          {
            "i": 733,
            "j": 594,
            "d": "NLNNLN",
            "o": "8571",
            "l": 1
          }
        ],
        [
          {
            "i": 735,
            "j": 590,
            "d": "NLNLNLNLMKNLNLNLOMNNLNLNMOMOLNLNLNLNLNKMLL",
            "o": "7799644786538711122191",
            "l": 1
          }
        ],
        [
          {
            "i": 859,
            "j": 618,
            "d": "NLOMNNLNKM",
            "o": "998121",
            "l": 1
          }
        ],
        [
          {
            "i": 891,
            "j": 714,
            "d": "NLNNLN",
            "o": "9900",
            "l": 1
          }
        ],
        [
          {
            "i": 1051,
            "j": 738,
            "d": "NLOMNNLNKM",
            "o": "996330",
            "l": 1
          }
        ],
        [
          {
            "i": 1075,
            "j": 734,
            "d": "NLNNNNNLNLOMNNNNOMNNNNOMOMNNNNNNMOLNLNLNKMLLLLKMLLLLLLLLKMKMKMLLMK",
            "o": "8960599007325555334222285555603284",
            "l": 1
          }
        ]
      ]
    },
    {
      "color": "2a933b",
      "shapes": [
        [
          {
            "i": 731,
            "j": 290,
            "d": "NLNNLN",
            "o": "5723",
            "l": 2
          }
        ]
      ]
    },
    {
      "color": "ffffff",
      "shapes": [
        [
          {
            "i": 731,
            "j": 582,
            "d": "MONNOMNLMKNLNLLLLNLNKM",
            "o": "880637320008",
            "l": 1
          }
        ],
        [
          {
            "i": 751,
            "j": 596,
            "d": "NNNLLL",
            "o": "9099",
            "l": 1
          }
        ],
        [
          {
            "i": 747,
            "j": 858,
            "d": "MO",
            "o": "13",
            "l": 1
          }
        ],
        [
          {
            "i": 861,
            "j": 634,
            "d": "NNOMNLLLKM",
            "o": "821307",
            "l": 1
          }
        ],
        [
          {
            "i": 851,
            "j": 738,
            "d": "NNNLLL",
            "o": "6975",
            "l": 1
          }
        ],
        [
          {
            "i": 967,
            "j": 722,
            "d": "NNNLLL",
            "o": "7665",
            "l": 1
          }
        ],
        [
          {
            "i": 989,
            "j": 730,
            "d": "NNNLLL",
            "o": "8218",
            "l": 1
          }
        ],
        [
          {
            "i": 1097,
            "j": 696,
            "d": "NNNLLL",
            "o": "9214",
            "l": 1
          }
        ]
      ]
    },
    {
      "color": "333e48",
      "shapes": [
        [
          {
            "i": 746,
            "j": 859,
            "d": "LNOOMK",
            "o": "8093",
            "l": 1
          }
        ],
        [
          {
            "i": 1051,
            "j": 774,
            "d": "MONNOMNLLLLLLL",
            "o": "76395459",
            "l": 1
          }
        ]
      ]
    }
  ]
}
