{
  "coords": {
    "system": "LV95",
    "x_min": 255.5,
    "x_max": 964.5,
    "x_count": 710,
    "y_min": -159.5,
    "y_max": 479.5,
    "y_count": 640
  },
  "areas": [
    {
      "color": "9e849a",
      "shapes": [
        [
          {
            "i": 231,
            "j": 786,
            "d": "NLNNLN",
            "o": "6622",
            "l": 0
          }
        ],
        [
          {
            "i": 667,
            "j": 220,
            "d": "NLOMNNLNLNLNLL",
            "o": "88455118",
            "l": 0
          }
        ],
        [
          {
            "i": 695,
            "j": 140,
            "d": "NLNLNLOMNLNLNLNLOMNNNNNNLNLNLNKMKMKMLNLNKM",
            "o": "2233233999027711787887",
            "l": 0
          }
        ],
        [
          {
            "i": 713,
            "j": 310,
            "d": "NLNLNLOMNLNLNNMOLNLNLNKMLNLNLL",
            "o": "7732003666574409",
            "l": 0
          }
        ],
        [
          {
            "i": 715,
            "j": 302,
            "d": "NLNNLN",
            "o": "2268",
            "l": 0
          }
        ],
        [
          {
            "i": 721,
            "j": 298,
            "d": "NLOMOMNNLNKMLNLNLL",
            "o": "4644335652",
            "l": 0
          }
        ],
        [
          {
            "i": 723,
            "j": 290,
            "d": "NLNNLN",
            "o": "2355",
            "l": 0
          }
        ],
        [
          {
            "i": 725,
            "j": 286,
            "d": "NLNNLN",
            "o": "2299",
            "l": 0
          }
        ],
        [
          {
            "i": 725,
            "j": 292,
            "d": "NLOMNLNLOMNNLNLNLNKMLNLNLL",
            "o": "44022278879226",
            "l": 0
          }
        ],
        [
          {
            "i": 739,
            "j": 312,
            "d": "NLNNLN",
            "o": "4498",
            "l": 0
          }
        ],
        [
          {
            "i": 749,
            "j": 324,
            "d": "NLOMNNMOLNKMLL",
            "o": "77900009",
            "l": 0
          }
        ],
        [
          {
            "i": 755,
            "j": 320,
            "d": "NLNNLN",
            "o": "3276",
            "l": 0
          }
        ],
        [
          {
            "i": 757,
            "j": 318,
            "d": "NLNNLN",
            "o": "2497",
            "l": 0
          }
        ],
        [
          {
            "i": 761,
            "j": 318,
            "d": "NLNNLN",
            "o": "2512",
            "l": 0
          }
        ],
        [
          {
            "i": 763,
            "j": 322,
            "d": "NLNNLN",
            "o": "9900",
            "l": 0
          }
        ],
        [
          {
            "i": 783,
            "j": 368,
            "d": "NLOMNNLNKM",
            "o": "551774",
            "l": 0
          }
        ],
        [
          {
            "i": 785,
            "j": 342,
            "d": "NLNNLN",
            "o": "7721",
            "l": 0
          }
        ],
        [
          {
            "i": 919,
            "j": 226,
            "d": "NLNNLN",
            "o": "8900",
            "l": 0
          }
        ],
        [
          {
            "i": 957,
            "j": 292,
            "d": "NLNNLN",
            "o": "7732",
            "l": 0
          }
        ],
        [
          {
            "i": 1091,
            "j": 80,
            "d": "NLOMNNNNOMNNNNNNLNKMLLLLLNLNLLLLLL",
            "o": "224715447572722772",
            "l": 0
          }
        ],
        [
          {
            "i": 1101,
            "j": 86,
            "d": "NLOMNNLNKM",
            "o": "744552",
            "l": 0
          }
        ]
      ]
    },
    {
      "color": "2a00fa",
      "shapes": [
        [
          {
            "i": 697,
            "j": 140,
            "d": "NLNNLN",
            "o": "8900",
            "l": 1
          }
        ],
        [
          {
            "i": 701,
            "j": 138,
            "d": "NLNNLN",
            "o": "4731",
            "l": 1
          }
        ]
      ]
    }
  ]
}
